{
  "strategy_name": "GKD_FisherTransform",
  "params": {
    "buy": {
      "atr_period": 21,
      "baseline_period": 7,
      "fisher_buy_threshold": -0.59,
      "fisher_period": 14,
      "fisher_smooth": 5,
      "goldie_locks": 2.73
    },
    "sell": {
      "fisher_sell_threshold": 3.62
    },
    "protection": {},
    "roi": {
      "0": 0.22100000000000003,
      "2705": 0.14200000000000002,
      "7098": 0.077,
      "11679": 0
    },
    "stoploss": {
      "stoploss": -0.092
    },
    "trailing": {
      "trailing_stop": true,
      "trailing_stop_positive": 0.01,
      "trailing_stop_positive_offset": 0.066,
      "trailing_only_offset_is_reached": true
    },
    "max_open_trades": {
      "max_open_trades": 3
    }
  },
  "ft_stratparam_v": 1,
  "export_time": "2025-07-15 02:36:16.364575+00:00"
}